Metadata-Version: 2.1
Name: verom_balex1
Version: 0.0.1
Summary: Print Stars
Author: Balex
Author-email: morevbalex777@gmail.com
